tacozip/__init__.py
tacozip/bindings.py
tacozip/config.py
tacozip/exceptions.py
tacozip/libtacozip.so
tacozip/loader.py
tacozip/version.py
tacozip.libs/libzip-5cb36f11.so.5.5
tacozip-0.10.2.dist-info/METADATA
tacozip-0.10.2.dist-info/WHEEL
tacozip-0.10.2.dist-info/entry_points.txt
tacozip-0.10.2.dist-info/top_level.txt
tacozip-0.10.2.dist-info/RECORD
